[{"payload": {"action": "created", "comment": {"body": "It should work with the defaults. That may change in the future, in which case looking at https://github.com/puppetlabs/cfacter/blob/master/contrib/cfacter.ps1 or its future replacement will give more specific instructions.", "url": "https://api.github.com/repos/puppetlabs/cfacter/issues/comments/77269019", "created_at": "2015-03-04T22:57:09Z", "html_url": "https://github.com/puppetlabs/cfacter/pull/323#issuecomment-77269019", "updated_at": "2015-03-04T22:57:09Z", "user": {"following_url": "https://api.github.com/users/MikaelSmith/following{/other_user}", "events_url": "https://api.github.com/users/MikaelSmith/events{/privacy}", "organizations_url": "https://api.github.com/users/MikaelSmith/orgs", "url": "https://api.github.com/users/MikaelSmith", "gists_url": "https://api.github.com/users/MikaelSmith/gists{/gist_id}", "html_url": "https://github.com/MikaelSmith", "subscriptions_url": "https://api.github.com/users/MikaelSmith/subscriptions", "avatar_url": "https://avatars.githubusercontent.com/u/8162496?v=3", "repos_url": "https://api.github.com/users/MikaelSmith/repos", "received_events_url": "https://api.github.com/users/MikaelSmith/received_events", "gravatar_id": "", "starred_url": "https://api.github.com/users/MikaelSmith/starred{/owner}{/repo}", "site_admin": false, "login": "MikaelSmith", "type": "User", "id": 8162496, "followers_url": "https://api.github.com/users/MikaelSmith/followers"}, "id": 77269019, "issue_url": "https://api.github.com/repos/puppetlabs/cfacter/issues/323"}, "issue": {"body": "Removes multiple sources of build documentation for Windows, and\r\nprovides links for Chocolatey packages where appropriate.\r\n\r\nSpecific MinGW-w64 settings are removed from the README to avoid\r\npackaging issues; the packaging configuration contains more details.", "labels": [], "locked": false, "title": "(doc) Update build docs for Windows", "url": "https://api.github.com/repos/puppetlabs/cfacter/issues/323", "labels_url": "https://api.github.com/repos/puppetlabs/cfacter/issues/323/labels{/name}", "created_at": "2015-03-04T21:52:05Z", "events_url": "https://api.github.com/repos/puppetlabs/cfacter/issues/323/events", "comments_url": "https://api.github.com/repos/puppetlabs/cfacter/issues/323/comments", "html_url": "https://github.com/puppetlabs/cfacter/pull/323", "comments": 3, "number": 323, "updated_at": "2015-03-04T22:57:09Z", "assignee": null, "state": "open", "user": {"following_url": "https://api.github.com/users/MikaelSmith/following{/other_user}", "events_url": "https://api.github.com/users/MikaelSmith/events{/privacy}", "organizations_url": "https://api.github.com/users/MikaelSmith/orgs", "url": "https://api.github.com/users/MikaelSmith", "gists_url": "https://api.github.com/users/MikaelSmith/gists{/gist_id}", "html_url": "https://github.com/MikaelSmith", "subscriptions_url": "https://api.github.com/users/MikaelSmith/subscriptions", "avatar_url": "https://avatars.githubusercontent.com/u/8162496?v=3", "repos_url": "https://api.github.com/users/MikaelSmith/repos", "received_events_url": "https://api.github.com/users/MikaelSmith/received_events", "gravatar_id": "", "starred_url": "https://api.github.com/users/MikaelSmith/starred{/owner}{/repo}", "site_admin": false, "login": "MikaelSmith", "type": "User", "id": 8162496, "followers_url": "https://api.github.com/users/MikaelSmith/followers"}, "milestone": null, "closed_at": null, "pull_request": {"url": "https://api.github.com/repos/puppetlabs/cfacter/pulls/323", "diff_url": "https://github.com/puppetlabs/cfacter/pull/323.diff", "html_url": "https://github.com/puppetlabs/cfacter/pull/323", "patch_url": "https://github.com/puppetlabs/cfacter/pull/323.patch"}, "id": 59868055}}, "created_at": "2015-03-04T22:57:09Z", "actor": {"url": "https://api.github.com/users/MikaelSmith", "login": "MikaelSmith", "avatar_url": "https://avatars.githubusercontent.com/u/8162496?", "id": 8162496, "gravatar_id": ""}, "id": "2625207296", "repo": {"url": "https://api.github.com/repos/puppetlabs/cfacter", "id": 17602228, "name": "puppetlabs/cfacter"}, "org": {"url": "https://api.github.com/orgs/puppetlabs", "login": "puppetlabs", "avatar_url": "https://avatars.githubusercontent.com/u/234268?", "id": 234268, "gravatar_id": ""}, "type": "IssueCommentEvent", "public": true}, {"payload": {"master_branch": "master", "ref_type": "repository", "ref": null, "description": "Phoca Gallery FinderPlugin is Joomla! CMS extension. Plugin which adds finder information of images in search results.", "pusher_type": "user"}, "created_at": "2015-03-04T22:57:09Z", "actor": {"url": "https://api.github.com/users/PhocaCz", "login": "PhocaCz", "avatar_url": "https://avatars.githubusercontent.com/u/5381559?", "id": 5381559, "gravatar_id": ""}, "id": "2625207288", "repo": {"url": "https://api.github.com/repos/PhocaCz/PhocaGalleryFinderPlugin", "id": 31684433, "name": "PhocaCz/PhocaGalleryFinderPlugin"}, "type": "CreateEvent", "public": true}, {"payload": {"size": 1, "head": "615f69977e57fdd0fddfdb8afaa49639e30219c4", "commits": [{"distinct": true, "sha": "615f69977e57fdd0fddfdb8afaa49639e30219c4", "message": "Reset", "url": "https://api.github.com/repos/allisonlindner/PUC-Jogos-Digitais/commits/615f69977e57fdd0fddfdb8afaa49639e30219c4", "author": {"email": "allison.lindner@LTCH0314.cwbdis.pucpr.br", "name": "unknown"}}], "distinct_size": 1, "push_id": 592230513, "ref": "refs/heads/master", "before": "a392d6bdc3c6e51ae019314051398514d2a135df"}, "created_at": "2015-03-04T22:57:09Z", "actor": {"url": "https://api.github.com/users/allisonlindner", "login": "allisonlindner", "avatar_url": "https://avatars.githubusercontent.com/u/7878259?", "id": 7878259, "gravatar_id": ""}, "id": "2625207287", "repo": {"url": "https://api.github.com/repos/allisonlindner/PUC-Jogos-Digitais", "id": 31571909, "name": "allisonlindner/PUC-Jogos-Digitais"}, "type": "PushEvent", "public": true}, {"payload": {"size": 2, "head": "18ca774987c5158267b82ce0ffd7a3609ad1ba32", "commits": [{"distinct": true, "sha": "fad23966e8e5ce9972bd33b2b9578b5db13926f3", "message": "update contribution guide with linting info", "url": "https://api.github.com/repos/node-schedule/node-schedule/commits/fad23966e8e5ce9972bd33b2b9578b5db13926f3", "author": {"email": "jon.d.hester@gmail.com", "name": "Jon Hester"}}, {"distinct": true, "sha": "18ca774987c5158267b82ce0ffd7a3609ad1ba32", "message": "Merge pull request #101 from jonhester/contribution-guide\n\nUpdate contribution guide with linting information", "url": "https://api.github.com/repos/node-schedule/node-schedule/commits/18ca774987c5158267b82ce0ffd7a3609ad1ba32", "author": {"email": "me@tejas.io", "name": "Tejas Manohar"}}], "distinct_size": 2, "push_id": 592230508, "ref": "refs/heads/master", "before": "f04d47e4205f97daf9bea09fb17672ec12dbefba"}, "created_at": "2015-03-04T22:57:09Z", "actor": {"url": "https://api.github.com/users/tejasmanohar", "login": "tejasmanohar", "avatar_url": "https://avatars.githubusercontent.com/u/5959235?", "id": 5959235, "gravatar_id": ""}, "id": "2625207270", "repo": {"url": "https://api.github.com/repos/node-schedule/node-schedule", "id": 1735515, "name": "node-schedule/node-schedule"}, "org": {"url": "https://api.github.com/orgs/node-schedule", "login": "node-schedule", "avatar_url": "https://avatars.githubusercontent.com/u/11254828?", "id": 11254828, "gravatar_id": ""}, "type": "PushEvent", "public": true}, {"payload": {"action": "created", "comment": {"body": "@srpearce Quick comment on your note re Google services. In the last sentences, \"might\" seems unnecessary. How about: \"We strongly suggest that you provide alternative resources for learners in these areas.\"", "url": "https://api.github.com/repos/edx/edx-documentation/issues/comments/77269015", "created_at": "2015-03-04T22:57:08Z", "html_url": "https://github.com/edx/edx-documentation/pull/186#issuecomment-77269015", "updated_at": "2015-03-04T22:57:08Z", "user": {"following_url": "https://api.github.com/users/catong/following{/other_user}", "events_url": "https://api.github.com/users/catong/events{/privacy}", "organizations_url": "https://api.github.com/users/catong/orgs", "url": "https://api.github.com/users/catong", "gists_url": "https://api.github.com/users/catong/gists{/gist_id}", "html_url": "https://github.com/catong", "subscriptions_url": "https://api.github.com/users/catong/subscriptions", "avatar_url": "https://avatars.githubusercontent.com/u/9041399?v=3", "repos_url": "https://api.github.com/users/catong/repos", "received_events_url": "https://api.github.com/users/catong/received_events", "gravatar_id": "", "starred_url": "https://api.github.com/users/catong/starred{/owner}{/repo}", "site_admin": false, "login": "catong", "type": "User", "id": 9041399, "followers_url": "https://api.github.com/users/catong/followers"}, "id": 77269015, "issue_url": "https://api.github.com/repos/edx/edx-documentation/issues/186"}, "issue": {"body": "@mhoeber @lamagnifica @catong Please review.", "labels": [], "locked": false, "title": "Sylvia/relnotes 3 4", "url": "https://api.github.com/repos/edx/edx-documentation/issues/186", "labels_url": "https://api.github.com/repos/edx/edx-documentation/issues/186/labels{/name}", "created_at": "2015-03-04T16:56:29Z", "events_url": "https://api.github.com/repos/edx/edx-documentation/issues/186/events", "comments_url": "https://api.github.com/repos/edx/edx-documentation/issues/186/comments", "html_url": "https://github.com/edx/edx-documentation/pull/186", "comments": 8, "number": 186, "updated_at": "2015-03-04T22:57:08Z", "assignee": null, "state": "open", "user": {"following_url": "https://api.github.com/users/srpearce/following{/other_user}", "events_url": "https://api.github.com/users/srpearce/events{/privacy}", "organizations_url": "https://api.github.com/users/srpearce/orgs", "url": "https://api.github.com/users/srpearce", "gists_url": "https://api.github.com/users/srpearce/gists{/gist_id}", "html_url": "https://github.com/srpearce", "subscriptions_url": "https://api.github.com/users/srpearce/subscriptions", "avatar_url": "https://avatars.githubusercontent.com/u/3493253?v=3", "repos_url": "https://api.github.com/users/srpearce/repos", "received_events_url": "https://api.github.com/users/srpearce/received_events", "gravatar_id": "", "starred_url": "https://api.github.com/users/srpearce/starred{/owner}{/repo}", "site_admin": false, "login": "srpearce", "type": "User", "id": 3493253, "followers_url": "https://api.github.com/users/srpearce/followers"}, "milestone": null, "closed_at": null, "pull_request": {"url": "https://api.github.com/repos/edx/edx-documentation/pulls/186", "diff_url": "https://github.com/edx/edx-documentation/pull/186.diff", "html_url": "https://github.com/edx/edx-documentation/pull/186", "patch_url": "https://github.com/edx/edx-documentation/pull/186.patch"}, "id": 59826681}}, "created_at": "2015-03-04T22:57:09Z", "actor": {"url": "https://api.github.com/users/catong", "login": "catong", "avatar_url": "https://avatars.githubusercontent.com/u/9041399?", "id": 9041399, "gravatar_id": ""}, "id": "2625207268", "repo": {"url": "https://api.github.com/repos/edx/edx-documentation", "id": 23839256, "name": "edx/edx-documentation"}, "org": {"url": "https://api.github.com/orgs/edx", "login": "edx", "avatar_url": "https://avatars.githubusercontent.com/u/3179841?", "id": 3179841, "gravatar_id": ""}, "type": "IssueCommentEvent", "public": true}, {"payload": {"action": "created", "comment": {"body": "ack\r\n\r\nI really like the new events page. Way better", "url": "https://api.github.com/repos/crate/crate-web/issues/comments/77269014", "created_at": "2015-03-04T22:57:08Z", "html_url": "https://github.com/crate/crate-web/pull/63#issuecomment-77269014", "updated_at": "2015-03-04T22:57:08Z", "user": {"following_url": "https://api.github.com/users/tbrandles/following{/other_user}", "events_url": "https://api.github.com/users/tbrandles/events{/privacy}", "organizations_url": "https://api.github.com/users/tbrandles/orgs", "url": "https://api.github.com/users/tbrandles", "gists_url": "https://api.github.com/users/tbrandles/gists{/gist_id}", "html_url": "https://github.com/tbrandles", "subscriptions_url": "https://api.github.com/users/tbrandles/subscriptions", "avatar_url": "https://avatars.githubusercontent.com/u/583474?v=3", "repos_url": "https://api.github.com/users/tbrandles/repos", "received_events_url": "https://api.github.com/users/tbrandles/received_events", "gravatar_id": "", "starred_url": "https://api.github.com/users/tbrandles/starred{/owner}{/repo}", "site_admin": false, "login": "tbrandles", "type": "User", "id": 583474, "followers_url": "https://api.github.com/users/tbrandles/followers"}, "id": 77269014, "issue_url": "https://api.github.com/repos/crate/crate-web/issues/63"}, "issue": {"body": "show upcoming events ascending by date\r\nshow past events descending by date\r\nshow 3 most recent upcoming events on frontpage\r\nimproved some event pages", "labels": [], "locked": false, "title": "improved events listing", "url": "https://api.github.com/repos/crate/crate-web/issues/63", "labels_url": "https://api.github.com/repos/crate/crate-web/issues/63/labels{/name}", "created_at": "2015-03-04T18:36:22Z", "events_url": "https://api.github.com/repos/crate/crate-web/issues/63/events", "comments_url": "https://api.github.com/repos/crate/crate-web/issues/63/comments", "html_url": "https://github.com/crate/crate-web/pull/63", "comments": 1, "number": 63, "updated_at": "2015-03-04T22:57:08Z", "assignee": null, "state": "open", "user": {"following_url": "https://api.github.com/users/chaudum/following{/other_user}", "events_url": "https://api.github.com/users/chaudum/events{/privacy}", "organizations_url": "https://api.github.com/users/chaudum/orgs", "url": "https://api.github.com/users/chaudum", "gists_url": "https://api.github.com/users/chaudum/gists{/gist_id}", "html_url": "https://github.com/chaudum", "subscriptions_url": "https://api.github.com/users/chaudum/subscriptions", "avatar_url": "https://avatars.githubusercontent.com/u/281260?v=3", "repos_url": "https://api.github.com/users/chaudum/repos", "received_events_url": "https://api.github.com/users/chaudum/received_events", "gravatar_id": "", "starred_url": "https://api.github.com/users/chaudum/starred{/owner}{/repo}", "site_admin": false, "login": "chaudum", "type": "User", "id": 281260, "followers_url": "https://api.github.com/users/chaudum/followers"}, "milestone": null, "closed_at": null, "pull_request": {"url": "https://api.github.com/repos/crate/crate-web/pulls/63", "diff_url": "https://github.com/crate/crate-web/pull/63.diff", "html_url": "https://github.com/crate/crate-web/pull/63", "patch_url": "https://github.com/crate/crate-web/pull/63.patch"}, "id": 59840733}}, "created_at": "2015-03-04T22:57:08Z", "actor": {"url": "https://api.github.com/users/tbrandles", "login": "tbrandles", "avatar_url": "https://avatars.githubusercontent.com/u/583474?", "id": 583474, "gravatar_id": ""}, "id": "2625207266", "repo": {"url": "https://api.github.com/repos/crate/crate-web", "id": 28360868, "name": "crate/crate-web"}, "org": {"url": "https://api.github.com/orgs/crate", "login": "crate", "avatar_url": "https://avatars.githubusercontent.com/u/4048232?", "id": 4048232, "gravatar_id": ""}, "type": "IssueCommentEvent", "public": true}, {"payload": {"size": 1, "head": "35e870595a48ce959995b66404225d820253b021", "commits": [{"distinct": true, "sha": "35e870595a48ce959995b66404225d820253b021", "message": "Update iphone-theme-tumblr.html", "url": "https://api.github.com/repos/touchandswipe/bravefrontier/commits/35e870595a48ce959995b66404225d820253b021", "author": {"email": "greenpuck55@gmail.com", "name": "Sam GreenP"}}], "distinct_size": 1, "push_id": 592230505, "ref": "refs/heads/gh-pages", "before": "46c379ef579417f2d5b6258c0380e2eafbd53029"}, "created_at": "2015-03-04T22:57:08Z", "actor": {"url": "https://api.github.com/users/touchandswipe", "login": "touchandswipe", "avatar_url": "https://avatars.githubusercontent.com/u/8906777?", "id": 8906777, "gravatar_id": ""}, "id": "2625207262", "repo": {"url": "https://api.github.com/repos/touchandswipe/bravefrontier", "id": 24437980, "name": "touchandswipe/bravefrontier"}, "type": "PushEvent", "public": true}, {"payload": {"action": "created", "comment": {"body": "Change monkey patched and tested on jobs", "url": "https://api.github.com/repos/wballard/starphleet/issues/comments/77269013", "created_at": "2015-03-04T22:57:08Z", "html_url": "https://github.com/wballard/starphleet/pull/184#issuecomment-77269013", "updated_at": "2015-03-04T22:57:08Z", "user": {"following_url": "https://api.github.com/users/benjamin7062/following{/other_user}", "events_url": "https://api.github.com/users/benjamin7062/events{/privacy}", "organizations_url": "https://api.github.com/users/benjamin7062/orgs", "url": "https://api.github.com/users/benjamin7062", "gists_url": "https://api.github.com/users/benjamin7062/gists{/gist_id}", "html_url": "https://github.com/benjamin7062", "subscriptions_url": "https://api.github.com/users/benjamin7062/subscriptions", "avatar_url": "https://avatars.githubusercontent.com/u/7997948?v=3", "repos_url": "https://api.github.com/users/benjamin7062/repos", "received_events_url": "https://api.github.com/users/benjamin7062/received_events", "gravatar_id": "", "starred_url": "https://api.github.com/users/benjamin7062/starred{/owner}{/repo}", "site_admin": false, "login": "benjamin7062", "type": "User", "id": 7997948, "followers_url": "https://api.github.com/users/benjamin7062/followers"}, "id": 77269013, "issue_url": "https://api.github.com/repos/wballard/starphleet/issues/184"}, "issue": {"body": "- if the corresponding beta user file doesn't exist skip the conf\r\n  for nginx", "labels": [], "locked": false, "title": "Don't create a conf for a non-existing beta", "url": "https://api.github.com/repos/wballard/starphleet/issues/184", "labels_url": "https://api.github.com/repos/wballard/starphleet/issues/184/labels{/name}", "created_at": "2015-03-04T22:45:27Z", "events_url": "https://api.github.com/repos/wballard/starphleet/issues/184/events", "comments_url": "https://api.github.com/repos/wballard/starphleet/issues/184/comments", "html_url": "https://github.com/wballard/starphleet/pull/184", "comments": 1, "number": 184, "updated_at": "2015-03-04T22:57:08Z", "assignee": null, "state": "open", "user": {"following_url": "https://api.github.com/users/benjamin7062/following{/other_user}", "events_url": "https://api.github.com/users/benjamin7062/events{/privacy}", "organizations_url": "https://api.github.com/users/benjamin7062/orgs", "url": "https://api.github.com/users/benjamin7062", "gists_url": "https://api.github.com/users/benjamin7062/gists{/gist_id}", "html_url": "https://github.com/benjamin7062", "subscriptions_url": "https://api.github.com/users/benjamin7062/subscriptions", "avatar_url": "https://avatars.githubusercontent.com/u/7997948?v=3", "repos_url": "https://api.github.com/users/benjamin7062/repos", "received_events_url": "https://api.github.com/users/benjamin7062/received_events", "gravatar_id": "", "starred_url": "https://api.github.com/users/benjamin7062/starred{/owner}{/repo}", "site_admin": false, "login": "benjamin7062", "type": "User", "id": 7997948, "followers_url": "https://api.github.com/users/benjamin7062/followers"}, "milestone": null, "closed_at": null, "pull_request": {"url": "https://api.github.com/repos/wballard/starphleet/pulls/184", "diff_url": "https://github.com/wballard/starphleet/pull/184.diff", "html_url": "https://github.com/wballard/starphleet/pull/184", "patch_url": "https://github.com/wballard/starphleet/pull/184.patch"}, "id": 59875140}}, "created_at": "2015-03-04T22:57:08Z", "actor": {"url": "https://api.github.com/users/benjamin7062", "login": "benjamin7062", "avatar_url": "https://avatars.githubusercontent.com/u/7997948?", "id": 7997948, "gravatar_id": ""}, "id": "2625207261", "repo": {"url": "https://api.github.com/repos/wballard/starphleet", "id": 12470761, "name": "wballard/starphleet"}, "type": "IssueCommentEvent", "public": true}, {"payload": {"forkee": {"issues_url": "https://api.github.com/repos/s3than/BoxPacker/issues{/number}", "stargazers_count": 0, "forks_url": "https://api.github.com/repos/s3than/BoxPacker/forks", "mirror_url": null, "subscription_url": "https://api.github.com/repos/s3than/BoxPacker/subscription", "notifications_url": "https://api.github.com/repos/s3than/BoxPacker/notifications{?since,all,participating}", "collaborators_url": "https://api.github.com/repos/s3than/BoxPacker/collaborators{/collaborator}", "updated_at": "2015-02-24T01:18:14Z", "private": false, "pulls_url": "https://api.github.com/repos/s3than/BoxPacker/pulls{/number}", "issue_comment_url": "https://api.github.com/repos/s3than/BoxPacker/issues/comments{/number}", "labels_url": "https://api.github.com/repos/s3than/BoxPacker/labels{/name}", "has_wiki": true, "full_name": "s3than/BoxPacker", "owner": {"following_url": "https://api.github.com/users/s3than/following{/other_user}", "events_url": "https://api.github.com/users/s3than/events{/privacy}", "organizations_url": "https://api.github.com/users/s3than/orgs", "url": "https://api.github.com/users/s3than", "gists_url": "https://api.github.com/users/s3than/gists{/gist_id}", "html_url": "https://github.com/s3than", "subscriptions_url": "https://api.github.com/users/s3than/subscriptions", "avatar_url": "https://avatars.githubusercontent.com/u/6881648?v=3", "repos_url": "https://api.github.com/users/s3than/repos", "received_events_url": "https://api.github.com/users/s3than/received_events", "gravatar_id": "", "starred_url": "https://api.github.com/users/s3than/starred{/owner}{/repo}", "site_admin": false, "login": "s3than", "type": "User", "id": 6881648, "followers_url": "https://api.github.com/users/s3than/followers"}, "statuses_url": "https://api.github.com/repos/s3than/BoxPacker/statuses/{sha}", "id": 31684432, "keys_url": "https://api.github.com/repos/s3than/BoxPacker/keys{/key_id}", "description": "3D bin packing / knapsack problem solver", "tags_url": "https://api.github.com/repos/s3than/BoxPacker/tags", "downloads_url": "https://api.github.com/repos/s3than/BoxPacker/downloads", "assignees_url": "https://api.github.com/repos/s3than/BoxPacker/assignees{/user}", "contents_url": "https://api.github.com/repos/s3than/BoxPacker/contents/{+path}", "has_pages": false, "git_refs_url": "https://api.github.com/repos/s3than/BoxPacker/git/refs{/sha}", "open_issues_count": 0, "clone_url": "https://github.com/s3than/BoxPacker.git", "watchers_count": 0, "git_tags_url": "https://api.github.com/repos/s3than/BoxPacker/git/tags{/sha}", "milestones_url": "https://api.github.com/repos/s3than/BoxPacker/milestones{/number}", "languages_url": "https://api.github.com/repos/s3than/BoxPacker/languages", "size": 1976, "homepage": "", "public": true, "fork": true, "commits_url": "https://api.github.com/repos/s3than/BoxPacker/commits{/sha}", "releases_url": "https://api.github.com/repos/s3than/BoxPacker/releases{/id}", "issue_events_url": "https://api.github.com/repos/s3than/BoxPacker/issues/events{/number}", "archive_url": "https://api.github.com/repos/s3than/BoxPacker/{archive_format}{/ref}", "comments_url": "https://api.github.com/repos/s3than/BoxPacker/comments{/number}", "events_url": "https://api.github.com/repos/s3than/BoxPacker/events", "contributors_url": "https://api.github.com/repos/s3than/BoxPacker/contributors", "html_url": "https://github.com/s3than/BoxPacker", "forks": 0, "compare_url": "https://api.github.com/repos/s3than/BoxPacker/compare/{base}...{head}", "open_issues": 0, "git_url": "git://github.com/s3than/BoxPacker.git", "svn_url": "https://github.com/s3than/BoxPacker", "merges_url": "https://api.github.com/repos/s3than/BoxPacker/merges", "has_issues": false, "ssh_url": "git@github.com:s3than/BoxPacker.git", "blobs_url": "https://api.github.com/repos/s3than/BoxPacker/git/blobs{/sha}", "git_commits_url": "https://api.github.com/repos/s3than/BoxPacker/git/commits{/sha}", "hooks_url": "https://api.github.com/repos/s3than/BoxPacker/hooks", "has_downloads": true, "watchers": 0, "name": "BoxPacker", "language": null, "url": "https://api.github.com/repos/s3than/BoxPacker", "created_at": "2015-03-04T22:57:08Z", "pushed_at": "2014-12-02T21:09:00Z", "forks_count": 0, "default_branch": "master", "teams_url": "https://api.github.com/repos/s3than/BoxPacker/teams", "trees_url": "https://api.github.com/repos/s3than/BoxPacker/git/trees{/sha}", "branches_url": "https://api.github.com/repos/s3than/BoxPacker/branches{/branch}", "subscribers_url": "https://api.github.com/repos/s3than/BoxPacker/subscribers", "stargazers_url": "https://api.github.com/repos/s3than/BoxPacker/stargazers"}}, "created_at": "2015-03-04T22:57:08Z", "actor": {"url": "https://api.github.com/users/s3than", "login": "s3than", "avatar_url": "https://avatars.githubusercontent.com/u/6881648?", "id": 6881648, "gravatar_id": ""}, "id": "2625207260", "repo": {"url": "https://api.github.com/repos/dvdoug/BoxPacker", "id": 5562675, "name": "dvdoug/BoxPacker"}, "type": "ForkEvent", "public": true}, {"payload": {"size": 1, "head": "bd93b6a73fc5c50b26c2002549df1373dd4f9703", "commits": [{"distinct": true, "sha": "bd93b6a73fc5c50b26c2002549df1373dd4f9703", "message": "new code", "url": "https://api.github.com/repos/danny-daniel/CST205_Project2/commits/bd93b6a73fc5c50b26c2002549df1373dd4f9703", "author": {"email": "dmora@csumb.edu", "name": "danny-daniel"}}], "distinct_size": 1, "push_id": 592230504, "ref": "refs/heads/master", "before": "d39cd6f9286eaf25e66810f6da943acbd1c2db4d"}, "created_at": "2015-03-04T22:57:08Z", "actor": {"url": "https://api.github.com/users/danny-daniel", "login": "danny-daniel", "avatar_url": "https://avatars.githubusercontent.com/u/11321954?", "id": 11321954, "gravatar_id": ""}, "id": "2625207257", "repo": {"url": "https://api.github.com/repos/danny-daniel/CST205_Project2", "id": 31683394, "name": "danny-daniel/CST205_Project2"}, "type": "PushEvent", "public": true}, {"payload": {"action": "created", "comment": {"body": "@23Skidoo oh, yes please.", "url": "https://api.github.com/repos/haskell/cabal/issues/comments/77269012", "created_at": "2015-03-04T22:57:08Z", "html_url": "https://github.com/haskell/cabal/pull/2449#issuecomment-77269012", "updated_at": "2015-03-04T22:57:08Z", "user": {"following_url": "https://api.github.com/users/dcoutts/following{/other_user}", "events_url": "https://api.github.com/users/dcoutts/events{/privacy}", "organizations_url": "https://api.github.com/users/dcoutts/orgs", "url": "https://api.github.com/users/dcoutts", "gists_url": "https://api.github.com/users/dcoutts/gists{/gist_id}", "html_url": "https://github.com/dcoutts", "subscriptions_url": "https://api.github.com/users/dcoutts/subscriptions", "avatar_url": "https://avatars.githubusercontent.com/u/1339423?v=3", "repos_url": "https://api.github.com/users/dcoutts/repos", "received_events_url": "https://api.github.com/users/dcoutts/received_events", "gravatar_id": "", "starred_url": "https://api.github.com/users/dcoutts/starred{/owner}{/repo}", "site_admin": false, "login": "dcoutts", "type": "User", "id": 1339423, "followers_url": "https://api.github.com/users/dcoutts/followers"}, "id": 77269012, "issue_url": "https://api.github.com/repos/haskell/cabal/issues/2449"}, "issue": {"body": "Closes: https://github.com/haskell/cabal/issues/2447", "labels": [], "locked": false, "title": "cabal-install.cabal : Add missing test dependency.", "url": "https://api.github.com/repos/haskell/cabal/issues/2449", "labels_url": "https://api.github.com/repos/haskell/cabal/issues/2449/labels{/name}", "created_at": "2015-03-04T00:01:24Z", "events_url": "https://api.github.com/repos/haskell/cabal/issues/2449/events", "comments_url": "https://api.github.com/repos/haskell/cabal/issues/2449/comments", "html_url": "https://github.com/haskell/cabal/pull/2449", "comments": 2, "number": 2449, "updated_at": "2015-03-04T22:57:08Z", "assignee": null, "state": "closed", "user": {"following_url": "https://api.github.com/users/erikd/following{/other_user}", "events_url": "https://api.github.com/users/erikd/events{/privacy}", "organizations_url": "https://api.github.com/users/erikd/orgs", "url": "https://api.github.com/users/erikd", "gists_url": "https://api.github.com/users/erikd/gists{/gist_id}", "html_url": "https://github.com/erikd", "subscriptions_url": "https://api.github.com/users/erikd/subscriptions", "avatar_url": "https://avatars.githubusercontent.com/u/307277?v=3", "repos_url": "https://api.github.com/users/erikd/repos", "received_events_url": "https://api.github.com/users/erikd/received_events", "gravatar_id": "", "starred_url": "https://api.github.com/users/erikd/starred{/owner}{/repo}", "site_admin": false, "login": "erikd", "type": "User", "id": 307277, "followers_url": "https://api.github.com/users/erikd/followers"}, "milestone": null, "closed_at": "2015-03-04T00:23:31Z", "pull_request": {"url": "https://api.github.com/repos/haskell/cabal/pulls/2449", "diff_url": "https://github.com/haskell/cabal/pull/2449.diff", "html_url": "https://github.com/haskell/cabal/pull/2449", "patch_url": "https://github.com/haskell/cabal/pull/2449.patch"}, "id": 59728146}}, "created_at": "2015-03-04T22:57:08Z", "actor": {"url": "https://api.github.com/users/dcoutts", "login": "dcoutts", "avatar_url": "https://avatars.githubusercontent.com/u/1339423?", "id": 1339423, "gravatar_id": ""}, "id": "2625207256", "repo": {"url": "https://api.github.com/repos/haskell/cabal", "id": 3728161, "name": "haskell/cabal"}, "org": {"url": "https://api.github.com/orgs/haskell", "login": "haskell", "avatar_url": "https://avatars.githubusercontent.com/u/450574?", "id": 450574, "gravatar_id": ""}, "type": "IssueCommentEvent", "public": true}, {"payload": {"action": "closed", "number": 101, "pull_request": {"deletions": 1, "merge_commit_sha": "314adeb220a8c4008646d6b56e0f3d52634d7038", "number": 101, "assignee": null, "mergeable": null, "closed_at": "2015-03-04T22:57:08Z", "additions": 2, "statuses_url": "https://api.github.com/repos/node-schedule/node-schedule/statuses/fad23966e8e5ce9972bd33b2b9578b5db13926f3", "id": 30510221, "title": "Update contribution guide with linting information", "comments": 0, "merged_at": "2015-03-04T22:57:08Z", "state": "closed", "_links": {"review_comment": {"href": "https://api.github.com/repos/node-schedule/node-schedule/pulls/comments{/number}"}, "commits": {"href": "https://api.github.com/repos/node-schedule/node-schedule/pulls/101/commits"}, "self": {"href": "https://api.github.com/repos/node-schedule/node-schedule/pulls/101"}, "review_comments": {"href": "https://api.github.com/repos/node-schedule/node-schedule/pulls/101/comments"}, "html": {"href": "https://github.com/node-schedule/node-schedule/pull/101"}, "comments": {"href": "https://api.github.com/repos/node-schedule/node-schedule/issues/101/comments"}, "issue": {"href": "https://api.github.com/repos/node-schedule/node-schedule/issues/101"}, "statuses": {"href": "https://api.github.com/repos/node-schedule/node-schedule/statuses/fad23966e8e5ce9972bd33b2b9578b5db13926f3"}}, "changed_files": 1, "diff_url": "https://github.com/node-schedule/node-schedule/pull/101.diff", "issue_url": "https://api.github.com/repos/node-schedule/node-schedule/issues/101", "body": "", "head": {"repo": {"issues_url": "https://api.github.com/repos/jonhester/node-schedule/issues{/number}", "stargazers_count": 0, "forks_url": "https://api.github.com/repos/jonhester/node-schedule/forks", "mirror_url": null, "subscription_url": "https://api.github.com/repos/jonhester/node-schedule/subscription", "notifications_url": "https://api.github.com/repos/jonhester/node-schedule/notifications{?since,all,participating}", "collaborators_url": "https://api.github.com/repos/jonhester/node-schedule/collaborators{/collaborator}", "updated_at": "2015-03-04T22:14:14Z", "private": false, "pulls_url": "https://api.github.com/repos/jonhester/node-schedule/pulls{/number}", "issue_comment_url": "https://api.github.com/repos/jonhester/node-schedule/issues/comments{/number}", "labels_url": "https://api.github.com/repos/jonhester/node-schedule/labels{/name}", "has_wiki": true, "full_name": "jonhester/node-schedule", "owner": {"following_url": "https://api.github.com/users/jonhester/following{/other_user}", "events_url": "https://api.github.com/users/jonhester/events{/privacy}", "organizations_url": "https://api.github.com/users/jonhester/orgs", "url": "https://api.github.com/users/jonhester", "gists_url": "https://api.github.com/users/jonhester/gists{/gist_id}", "html_url": "https://github.com/jonhester", "subscriptions_url": "https://api.github.com/users/jonhester/subscriptions", "avatar_url": "https://avatars.githubusercontent.com/u/3527123?v=3", "repos_url": "https://api.github.com/users/jonhester/repos", "received_events_url": "https://api.github.com/users/jonhester/received_events", "gravatar_id": "", "starred_url": "https://api.github.com/users/jonhester/starred{/owner}{/repo}", "site_admin": false, "login": "jonhester", "type": "User", "id": 3527123, "followers_url": "https://api.github.com/users/jonhester/followers"}, "statuses_url": "https://api.github.com/repos/jonhester/node-schedule/statuses/{sha}", "id": 31422719, "keys_url": "https://api.github.com/repos/jonhester/node-schedule/keys{/key_id}", "description": "A cron-like and not-cron-like job scheduler for Node.", "tags_url": "https://api.github.com/repos/jonhester/node-schedule/tags", "downloads_url": "https://api.github.com/repos/jonhester/node-schedule/downloads", "assignees_url": "https://api.github.com/repos/jonhester/node-schedule/assignees{/user}", "contents_url": "https://api.github.com/repos/jonhester/node-schedule/contents/{+path}", "has_pages": false, "git_refs_url": "https://api.github.com/repos/jonhester/node-schedule/git/refs{/sha}", "open_issues_count": 0, "clone_url": "https://github.com/jonhester/node-schedule.git", "watchers_count": 0, "git_tags_url": "https://api.github.com/repos/jonhester/node-schedule/git/tags{/sha}", "milestones_url": "https://api.github.com/repos/jonhester/node-schedule/milestones{/number}", "languages_url": "https://api.github.com/repos/jonhester/node-schedule/languages", "size": 186, "homepage": "", "fork": true, "commits_url": "https://api.github.com/repos/jonhester/node-schedule/commits{/sha}", "releases_url": "https://api.github.com/repos/jonhester/node-schedule/releases{/id}", "issue_events_url": "https://api.github.com/repos/jonhester/node-schedule/issues/events{/number}", "archive_url": "https://api.github.com/repos/jonhester/node-schedule/{archive_format}{/ref}", "comments_url": "https://api.github.com/repos/jonhester/node-schedule/comments{/number}", "events_url": "https://api.github.com/repos/jonhester/node-schedule/events", "contributors_url": "https://api.github.com/repos/jonhester/node-schedule/contributors", "html_url": "https://github.com/jonhester/node-schedule", "forks": 0, "compare_url": "https://api.github.com/repos/jonhester/node-schedule/compare/{base}...{head}", "open_issues": 0, "git_url": "git://github.com/jonhester/node-schedule.git", "svn_url": "https://github.com/jonhester/node-schedule", "merges_url": "https://api.github.com/repos/jonhester/node-schedule/merges", "has_issues": false, "ssh_url": "git@github.com:jonhester/node-schedule.git", "blobs_url": "https://api.github.com/repos/jonhester/node-schedule/git/blobs{/sha}", "git_commits_url": "https://api.github.com/repos/jonhester/node-schedule/git/commits{/sha}", "hooks_url": "https://api.github.com/repos/jonhester/node-schedule/hooks", "has_downloads": true, "watchers": 0, "name": "node-schedule", "language": "JavaScript", "url": "https://api.github.com/repos/jonhester/node-schedule", "created_at": "2015-02-27T14:24:30Z", "pushed_at": "2015-03-04T22:43:18Z", "forks_count": 0, "default_branch": "master", "teams_url": "https://api.github.com/repos/jonhester/node-schedule/teams", "trees_url": "https://api.github.com/repos/jonhester/node-schedule/git/trees{/sha}", "branches_url": "https://api.github.com/repos/jonhester/node-schedule/branches{/branch}", "subscribers_url": "https://api.github.com/repos/jonhester/node-schedule/subscribers", "stargazers_url": "https://api.github.com/repos/jonhester/node-schedule/stargazers"}, "sha": "fad23966e8e5ce9972bd33b2b9578b5db13926f3", "ref": "contribution-guide", "user": {"following_url": "https://api.github.com/users/jonhester/following{/other_user}", "events_url": "https://api.github.com/users/jonhester/events{/privacy}", "organizations_url": "https://api.github.com/users/jonhester/orgs", "url": "https://api.github.com/users/jonhester", "gists_url": "https://api.github.com/users/jonhester/gists{/gist_id}", "html_url": "https://github.com/jonhester", "subscriptions_url": "https://api.github.com/users/jonhester/subscriptions", "avatar_url": "https://avatars.githubusercontent.com/u/3527123?v=3", "repos_url": "https://api.github.com/users/jonhester/repos", "received_events_url": "https://api.github.com/users/jonhester/received_events", "gravatar_id": "", "starred_url": "https://api.github.com/users/jonhester/starred{/owner}{/repo}", "site_admin": false, "login": "jonhester", "type": "User", "id": 3527123, "followers_url": "https://api.github.com/users/jonhester/followers"}, "label": "jonhester:contribution-guide"}, "commits_url": "https://api.github.com/repos/node-schedule/node-schedule/pulls/101/commits", "commits": 1, "comments_url": "https://api.github.com/repos/node-schedule/node-schedule/issues/101/comments", "html_url": "https://github.com/node-schedule/node-schedule/pull/101", "updated_at": "2015-03-04T22:57:08Z", "base": {"repo": {"issues_url": "https://api.github.com/repos/node-schedule/node-schedule/issues{/number}", "stargazers_count": 1075, "forks_url": "https://api.github.com/repos/node-schedule/node-schedule/forks", "mirror_url": null, "subscription_url": "https://api.github.com/repos/node-schedule/node-schedule/subscription", "notifications_url": "https://api.github.com/repos/node-schedule/node-schedule/notifications{?since,all,participating}", "collaborators_url": "https://api.github.com/repos/node-schedule/node-schedule/collaborators{/collaborator}", "updated_at": "2015-03-04T21:49:45Z", "private": false, "pulls_url": "https://api.github.com/repos/node-schedule/node-schedule/pulls{/number}", "issue_comment_url": "https://api.github.com/repos/node-schedule/node-schedule/issues/comments{/number}", "labels_url": "https://api.github.com/repos/node-schedule/node-schedule/labels{/name}", "has_wiki": true, "full_name": "node-schedule/node-schedule", "owner": {"following_url": "https://api.github.com/users/node-schedule/following{/other_user}", "events_url": "https://api.github.com/users/node-schedule/events{/privacy}", "organizations_url": "https://api.github.com/users/node-schedule/orgs", "url": "https://api.github.com/users/node-schedule", "gists_url": "https://api.github.com/users/node-schedule/gists{/gist_id}", "html_url": "https://github.com/node-schedule", "subscriptions_url": "https://api.github.com/users/node-schedule/subscriptions", "avatar_url": "https://avatars.githubusercontent.com/u/11254828?v=3", "repos_url": "https://api.github.com/users/node-schedule/repos", "received_events_url": "https://api.github.com/users/node-schedule/received_events", "gravatar_id": "", "starred_url": "https://api.github.com/users/node-schedule/starred{/owner}{/repo}", "site_admin": false, "login": "node-schedule", "type": "Organization", "id": 11254828, "followers_url": "https://api.github.com/users/node-schedule/followers"}, "statuses_url": "https://api.github.com/repos/node-schedule/node-schedule/statuses/{sha}", "id": 1735515, "keys_url": "https://api.github.com/repos/node-schedule/node-schedule/keys{/key_id}", "description": "A cron-like and not-cron-like job scheduler for Node.", "tags_url": "https://api.github.com/repos/node-schedule/node-schedule/tags", "downloads_url": "https://api.github.com/repos/node-schedule/node-schedule/downloads", "assignees_url": "https://api.github.com/repos/node-schedule/node-schedule/assignees{/user}", "contents_url": "https://api.github.com/repos/node-schedule/node-schedule/contents/{+path}", "has_pages": false, "git_refs_url": "https://api.github.com/repos/node-schedule/node-schedule/git/refs{/sha}", "open_issues_count": 2, "clone_url": "https://github.com/node-schedule/node-schedule.git", "watchers_count": 1075, "git_tags_url": "https://api.github.com/repos/node-schedule/node-schedule/git/tags{/sha}", "milestones_url": "https://api.github.com/repos/node-schedule/node-schedule/milestones{/number}", "languages_url": "https://api.github.com/repos/node-schedule/node-schedule/languages", "size": 1203, "homepage": "", "fork": false, "commits_url": "https://api.github.com/repos/node-schedule/node-schedule/commits{/sha}", "releases_url": "https://api.github.com/repos/node-schedule/node-schedule/releases{/id}", "issue_events_url": "https://api.github.com/repos/node-schedule/node-schedule/issues/events{/number}", "archive_url": "https://api.github.com/repos/node-schedule/node-schedule/{archive_format}{/ref}", "comments_url": "https://api.github.com/repos/node-schedule/node-schedule/comments{/number}", "events_url": "https://api.github.com/repos/node-schedule/node-schedule/events", "contributors_url": "https://api.github.com/repos/node-schedule/node-schedule/contributors", "html_url": "https://github.com/node-schedule/node-schedule", "forks": 81, "compare_url": "https://api.github.com/repos/node-schedule/node-schedule/compare/{base}...{head}", "open_issues": 2, "git_url": "git://github.com/node-schedule/node-schedule.git", "svn_url": "https://github.com/node-schedule/node-schedule", "merges_url": "https://api.github.com/repos/node-schedule/node-schedule/merges", "has_issues": true, "ssh_url": "git@github.com:node-schedule/node-schedule.git", "blobs_url": "https://api.github.com/repos/node-schedule/node-schedule/git/blobs{/sha}", "git_commits_url": "https://api.github.com/repos/node-schedule/node-schedule/git/commits{/sha}", "hooks_url": "https://api.github.com/repos/node-schedule/node-schedule/hooks", "has_downloads": true, "watchers": 1075, "name": "node-schedule", "language": "JavaScript", "url": "https://api.github.com/repos/node-schedule/node-schedule", "created_at": "2011-05-11T21:41:34Z", "pushed_at": "2015-03-04T22:57:08Z", "forks_count": 81, "default_branch": "master", "teams_url": "https://api.github.com/repos/node-schedule/node-schedule/teams", "trees_url": "https://api.github.com/repos/node-schedule/node-schedule/git/trees{/sha}", "branches_url": "https://api.github.com/repos/node-schedule/node-schedule/branches{/branch}", "subscribers_url": "https://api.github.com/repos/node-schedule/node-schedule/subscribers", "stargazers_url": "https://api.github.com/repos/node-schedule/node-schedule/stargazers"}, "sha": "f04d47e4205f97daf9bea09fb17672ec12dbefba", "ref": "master", "user": {"following_url": "https://api.github.com/users/node-schedule/following{/other_user}", "events_url": "https://api.github.com/users/node-schedule/events{/privacy}", "organizations_url": "https://api.github.com/users/node-schedule/orgs", "url": "https://api.github.com/users/node-schedule", "gists_url": "https://api.github.com/users/node-schedule/gists{/gist_id}", "html_url": "https://github.com/node-schedule", "subscriptions_url": "https://api.github.com/users/node-schedule/subscriptions", "avatar_url": "https://avatars.githubusercontent.com/u/11254828?v=3", "repos_url": "https://api.github.com/users/node-schedule/repos", "received_events_url": "https://api.github.com/users/node-schedule/received_events", "gravatar_id": "", "starred_url": "https://api.github.com/users/node-schedule/starred{/owner}{/repo}", "site_admin": false, "login": "node-schedule", "type": "Organization", "id": 11254828, "followers_url": "https://api.github.com/users/node-schedule/followers"}, "label": "node-schedule:master"}, "user": {"following_url": "https://api.github.com/users/jonhester/following{/other_user}", "events_url": "https://api.github.com/users/jonhester/events{/privacy}", "organizations_url": "https://api.github.com/users/jonhester/orgs", "url": "https://api.github.com/users/jonhester", "gists_url": "https://api.github.com/users/jonhester/gists{/gist_id}", "html_url": "https://github.com/jonhester", "subscriptions_url": "https://api.github.com/users/jonhester/subscriptions", "avatar_url": "https://avatars.githubusercontent.com/u/3527123?v=3", "repos_url": "https://api.github.com/users/jonhester/repos", "received_events_url": "https://api.github.com/users/jonhester/received_events", "gravatar_id": "", "starred_url": "https://api.github.com/users/jonhester/starred{/owner}{/repo}", "site_admin": false, "login": "jonhester", "type": "User", "id": 3527123, "followers_url": "https://api.github.com/users/jonhester/followers"}, "milestone": null, "locked": false, "merged_by": {"following_url": "https://api.github.com/users/tejasmanohar/following{/other_user}", "events_url": "https://api.github.com/users/tejasmanohar/events{/privacy}", "organizations_url": "https://api.github.com/users/tejasmanohar/orgs", "url": "https://api.github.com/users/tejasmanohar", "gists_url": "https://api.github.com/users/tejasmanohar/gists{/gist_id}", "html_url": "https://github.com/tejasmanohar", "subscriptions_url": "https://api.github.com/users/tejasmanohar/subscriptions", "avatar_url": "https://avatars.githubusercontent.com/u/5959235?v=3", "repos_url": "https://api.github.com/users/tejasmanohar/repos", "received_events_url": "https://api.github.com/users/tejasmanohar/received_events", "gravatar_id": "", "starred_url": "https://api.github.com/users/tejasmanohar/starred{/owner}{/repo}", "site_admin": false, "login": "tejasmanohar", "type": "User", "id": 5959235, "followers_url": "https://api.github.com/users/tejasmanohar/followers"}, "url": "https://api.github.com/repos/node-schedule/node-schedule/pulls/101", "mergeable_state": "unknown", "created_at": "2015-03-04T22:15:02Z", "merged": true, "review_comments_url": "https://api.github.com/repos/node-schedule/node-schedule/pulls/101/comments", "review_comments": 0, "review_comment_url": "https://api.github.com/repos/node-schedule/node-schedule/pulls/comments{/number}", "patch_url": "https://github.com/node-schedule/node-schedule/pull/101.patch"}}, "created_at": "2015-03-04T22:57:08Z", "actor": {"url": "https://api.github.com/users/tejasmanohar", "login": "tejasmanohar", "avatar_url": "https://avatars.githubusercontent.com/u/5959235?", "id": 5959235, "gravatar_id": ""}, "id": "2625207255", "repo": {"url": "https://api.github.com/repos/node-schedule/node-schedule", "id": 1735515, "name": "node-schedule/node-schedule"}, "org": {"url": "https://api.github.com/orgs/node-schedule", "login": "node-schedule", "avatar_url": "https://avatars.githubusercontent.com/u/11254828?", "id": 11254828, "gravatar_id": ""}, "type": "PullRequestEvent", "public": true}, {"payload": {"master_branch": "master", "ref_type": "branch", "ref": "master", "description": "", "pusher_type": "user"}, "created_at": "2015-03-04T22:57:08Z", "actor": {"url": "https://api.github.com/users/kumarswamykannu", "login": "kumarswamykannu", "avatar_url": "https://avatars.githubusercontent.com/u/11317811?", "id": 11317811, "gravatar_id": ""}, "id": "2625207252", "repo": {"url": "https://api.github.com/repos/kumarswamykannu/https-github.com-MicrosoftLearning-PythonSqlFlask", "id": 31684317, "name": "kumarswamykannu/https-github.com-MicrosoftLearning-PythonSqlFlask"}, "type": "CreateEvent", "public": true}, {"payload": {"size": 1, "head": "f11825b7fe122ab880aae749642c573a611006d0", "commits": [{"distinct": true, "sha": "f11825b7fe122ab880aae749642c573a611006d0", "message": "", "url": "https://api.github.com/repos/PhocaCz/PhocaPDFSystemPlugin/commits/f11825b7fe122ab880aae749642c573a611006d0", "author": {"email": "info@phoca.cz", "name": "Jan"}}], "distinct_size": 1, "push_id": 592230497, "ref": "refs/heads/master", "before": "aefe43cfb40dad03b68abb5cfdddc084a1084f3e"}, "created_at": "2015-03-04T22:57:08Z", "actor": {"url": "https://api.github.com/users/PhocaCz", "login": "PhocaCz", "avatar_url": "https://avatars.githubusercontent.com/u/5381559?", "id": 5381559, "gravatar_id": ""}, "id": "2625207247", "repo": {"url": "https://api.github.com/repos/PhocaCz/PhocaPDFSystemPlugin", "id": 31684431, "name": "PhocaCz/PhocaPDFSystemPlugin"}, "type": "PushEvent", "public": true}, {"payload": {"size": 1, "head": "30a76c3e67898a3a29d595e96b7ba9918dd2e227", "commits": [{"distinct": true, "sha": "30a76c3e67898a3a29d595e96b7ba9918dd2e227", "message": "fix IntensityValue not loading correctly", "url": "https://api.github.com/repos/SciAps/LIBZSharpen/commits/30a76c3e67898a3a29d595e96b7ba9918dd2e227", "author": {"email": "psoucy@sciaps.com", "name": "paul"}}], "distinct_size": 1, "push_id": 592230493, "ref": "refs/heads/master", "before": "0588c39df3a6d9e9787f56ba3058544a488241f5"}, "created_at": "2015-03-04T22:57:07Z", "actor": {"url": "https://api.github.com/users/dinocore1", "login": "dinocore1", "avatar_url": "https://avatars.githubusercontent.com/u/934623?", "id": 934623, "gravatar_id": ""}, "id": "2625207239", "repo": {"url": "https://api.github.com/repos/SciAps/LIBZSharpen", "id": 25648502, "name": "SciAps/LIBZSharpen"}, "org": {"url": "https://api.github.com/orgs/SciAps", "login": "SciAps", "avatar_url": "https://avatars.githubusercontent.com/u/4762925?", "id": 4762925, "gravatar_id": ""}, "type": "PushEvent", "public": true}, {"payload": {"size": 1, "head": "a9d30f5a67946aa34b904879b9e8031bed1be1ea", "commits": [{"distinct": true, "sha": "a9d30f5a67946aa34b904879b9e8031bed1be1ea", "message": "Give <collex:archive> the MJP id of the journal.", "url": "https://api.github.com/repos/cwulfman/ModNets/commits/a9d30f5a67946aa34b904879b9e8031bed1be1ea", "author": {"email": "cwulfman@princeton.edu", "name": "Cliff Wulfman"}}], "distinct_size": 1, "push_id": 592230490, "ref": "refs/heads/master", "before": "2a8a8e7c4baf95cef25e243d4708915a9a0200e7"}, "created_at": "2015-03-04T22:57:07Z", "actor": {"url": "https://api.github.com/users/cwulfman", "login": "cwulfman", "avatar_url": "https://avatars.githubusercontent.com/u/891097?", "id": 891097, "gravatar_id": ""}, "id": "2625207237", "repo": {"url": "https://api.github.com/repos/cwulfman/ModNets", "id": 12183296, "name": "cwulfman/ModNets"}, "type": "PushEvent", "public": true}, {"payload": {"master_branch": "master", "ref_type": "branch", "ref": "master", "description": "Phoca PDF System Plugin is Joomla! CMS extension. Plugin which adds PDF button/icon into Joomla! article.", "pusher_type": "user"}, "created_at": "2015-03-04T22:57:07Z", "actor": {"url": "https://api.github.com/users/PhocaCz", "login": "PhocaCz", "avatar_url": "https://avatars.githubusercontent.com/u/5381559?", "id": 5381559, "gravatar_id": ""}, "id": "2625207231", "repo": {"url": "https://api.github.com/repos/PhocaCz/PhocaPDFSystemPlugin", "id": 31684431, "name": "PhocaCz/PhocaPDFSystemPlugin"}, "type": "CreateEvent", "public": true}, {"payload": {"master_branch": "master", "ref_type": "branch", "ref": "role/timezone", "description": "A collection of Ansible stuff (mainly roles) for easy reuse in several codebases.", "pusher_type": "user"}, "created_at": "2015-03-04T22:57:07Z", "actor": {"url": "https://api.github.com/users/frenck", "login": "frenck", "avatar_url": "https://avatars.githubusercontent.com/u/195327?", "id": 195327, "gravatar_id": ""}, "id": "2625207221", "repo": {"url": "https://api.github.com/repos/GeekChimp/ansible-omnibus", "id": 31595603, "name": "GeekChimp/ansible-omnibus"}, "org": {"url": "https://api.github.com/orgs/GeekChimp", "login": "GeekChimp", "avatar_url": "https://avatars.githubusercontent.com/u/1467112?", "id": 1467112, "gravatar_id": ""}, "type": "CreateEvent", "public": true}, {"payload": {"master_branch": "master", "ref_type": "branch", "ref": "master", "description": "Django REST Framework Tutorial", "pusher_type": "user"}, "created_at": "2015-03-04T22:57:07Z", "actor": {"url": "https://api.github.com/users/astagi", "login": "astagi", "avatar_url": "https://avatars.githubusercontent.com/u/537363?", "id": 537363, "gravatar_id": ""}, "id": "2625207211", "repo": {"url": "https://api.github.com/repos/DjangoBeer/drf-tutorial", "id": 31684331, "name": "DjangoBeer/drf-tutorial"}, "org": {"url": "https://api.github.com/orgs/DjangoBeer", "login": "DjangoBeer", "avatar_url": "https://avatars.githubusercontent.com/u/11311146?", "id": 11311146, "gravatar_id": ""}, "type": "CreateEvent", "public": true}, {"payload": {"action": "closed", "issue": {"body": "", "labels": [{"url": "https://api.github.com/repos/greghunt/asgard/labels/bug", "color": "fc2929", "name": "bug"}], "locked": false, "title": "Remove interior text and just show pictures + titles for mobile", "url": "https://api.github.com/repos/greghunt/asgard/issues/9", "labels_url": "https://api.github.com/repos/greghunt/asgard/issues/9/labels{/name}", "created_at": "2015-03-03T01:30:39Z", "events_url": "https://api.github.com/repos/greghunt/asgard/issues/9/events", "comments_url": "https://api.github.com/repos/greghunt/asgard/issues/9/comments", "html_url": "https://github.com/greghunt/asgard/issues/9", "comments": 0, "number": 9, "updated_at": "2015-03-04T22:57:07Z", "assignee": {"following_url": "https://api.github.com/users/greghunt/following{/other_user}", "events_url": "https://api.github.com/users/greghunt/events{/privacy}", "organizations_url": "https://api.github.com/users/greghunt/orgs", "url": "https://api.github.com/users/greghunt", "gists_url": "https://api.github.com/users/greghunt/gists{/gist_id}", "html_url": "https://github.com/greghunt", "subscriptions_url": "https://api.github.com/users/greghunt/subscriptions", "avatar_url": "https://avatars.githubusercontent.com/u/1238407?v=3", "repos_url": "https://api.github.com/users/greghunt/repos", "received_events_url": "https://api.github.com/users/greghunt/received_events", "gravatar_id": "", "starred_url": "https://api.github.com/users/greghunt/starred{/owner}{/repo}", "site_admin": false, "login": "greghunt", "type": "User", "id": 1238407, "followers_url": "https://api.github.com/users/greghunt/followers"}, "state": "closed", "user": {"following_url": "https://api.github.com/users/Mcoppola16x/following{/other_user}", "events_url": "https://api.github.com/users/Mcoppola16x/events{/privacy}", "organizations_url": "https://api.github.com/users/Mcoppola16x/orgs", "url": "https://api.github.com/users/Mcoppola16x", "gists_url": "https://api.github.com/users/Mcoppola16x/gists{/gist_id}", "html_url": "https://github.com/Mcoppola16x", "subscriptions_url": "https://api.github.com/users/Mcoppola16x/subscriptions", "avatar_url": "https://avatars.githubusercontent.com/u/11283615?v=3", "repos_url": "https://api.github.com/users/Mcoppola16x/repos", "received_events_url": "https://api.github.com/users/Mcoppola16x/received_events", "gravatar_id": "", "starred_url": "https://api.github.com/users/Mcoppola16x/starred{/owner}{/repo}", "site_admin": false, "login": "Mcoppola16x", "type": "User", "id": 11283615, "followers_url": "https://api.github.com/users/Mcoppola16x/followers"}, "milestone": null, "closed_at": "2015-03-04T22:57:07Z", "id": 59581574}}, "created_at": "2015-03-04T22:57:07Z", "actor": {"url": "https://api.github.com/users/greghunt", "login": "greghunt", "avatar_url": "https://avatars.githubusercontent.com/u/1238407?", "id": 1238407, "gravatar_id": ""}, "id": "2625207205", "repo": {"url": "https://api.github.com/repos/greghunt/asgard", "id": 25102868, "name": "greghunt/asgard"}, "type": "IssuesEvent", "public": true}, {"payload": {"master_branch": "master", "ref_type": "repository", "ref": null, "description": "Phoca PDF System Plugin is Joomla! CMS extension. Plugin which adds PDF button/icon into Joomla! article.", "pusher_type": "user"}, "created_at": "2015-03-04T22:57:07Z", "actor": {"url": "https://api.github.com/users/PhocaCz", "login": "PhocaCz", "avatar_url": "https://avatars.githubusercontent.com/u/5381559?", "id": 5381559, "gravatar_id": ""}, "id": "2625207197", "repo": {"url": "https://api.github.com/repos/PhocaCz/PhocaPDFSystemPlugin", "id": 31684431, "name": "PhocaCz/PhocaPDFSystemPlugin"}, "type": "CreateEvent", "public": true}, {"payload": {"action": "opened", "number": 2, "pull_request": {"deletions": 1, "merge_commit_sha": null, "number": 2, "assignee": null, "mergeable": null, "closed_at": null, "additions": 4, "statuses_url": "https://api.github.com/repos/suihanki/suihanki.github.io/statuses/571ef42bcc16ae57a4dc137ff52729fd46971b27", "id": 30513652, "title": "Test branch", "comments": 0, "merged_at": null, "state": "open", "_links": {"review_comment": {"href": "https://api.github.com/repos/suihanki/suihanki.github.io/pulls/comments{/number}"}, "commits": {"href": "https://api.github.com/repos/suihanki/suihanki.github.io/pulls/2/commits"}, "self": {"href": "https://api.github.com/repos/suihanki/suihanki.github.io/pulls/2"}, "review_comments": {"href": "https://api.github.com/repos/suihanki/suihanki.github.io/pulls/2/comments"}, "html": {"href": "https://github.com/suihanki/suihanki.github.io/pull/2"}, "comments": {"href": "https://api.github.com/repos/suihanki/suihanki.github.io/issues/2/comments"}, "issue": {"href": "https://api.github.com/repos/suihanki/suihanki.github.io/issues/2"}, "statuses": {"href": "https://api.github.com/repos/suihanki/suihanki.github.io/statuses/571ef42bcc16ae57a4dc137ff52729fd46971b27"}}, "changed_files": 1, "diff_url": "https://github.com/suihanki/suihanki.github.io/pull/2.diff", "issue_url": "https://api.github.com/repos/suihanki/suihanki.github.io/issues/2", "body": "", "head": {"repo": {"issues_url": "https://api.github.com/repos/suihanki/suihanki.github.io/issues{/number}", "stargazers_count": 0, "forks_url": "https://api.github.com/repos/suihanki/suihanki.github.io/forks", "mirror_url": null, "subscription_url": "https://api.github.com/repos/suihanki/suihanki.github.io/subscription", "notifications_url": "https://api.github.com/repos/suihanki/suihanki.github.io/notifications{?since,all,participating}", "collaborators_url": "https://api.github.com/repos/suihanki/suihanki.github.io/collaborators{/collaborator}", "updated_at": "2015-03-04T22:49:09Z", "private": false, "pulls_url": "https://api.github.com/repos/suihanki/suihanki.github.io/pulls{/number}", "issue_comment_url": "https://api.github.com/repos/suihanki/suihanki.github.io/issues/comments{/number}", "labels_url": "https://api.github.com/repos/suihanki/suihanki.github.io/labels{/name}", "has_wiki": true, "full_name": "suihanki/suihanki.github.io", "owner": {"following_url": "https://api.github.com/users/suihanki/following{/other_user}", "events_url": "https://api.github.com/users/suihanki/events{/privacy}", "organizations_url": "https://api.github.com/users/suihanki/orgs", "url": "https://api.github.com/users/suihanki", "gists_url": "https://api.github.com/users/suihanki/gists{/gist_id}", "html_url": "https://github.com/suihanki", "subscriptions_url": "https://api.github.com/users/suihanki/subscriptions", "avatar_url": "https://avatars.githubusercontent.com/u/1302764?v=3", "repos_url": "https://api.github.com/users/suihanki/repos", "received_events_url": "https://api.github.com/users/suihanki/received_events", "gravatar_id": "", "starred_url": "https://api.github.com/users/suihanki/starred{/owner}{/repo}", "site_admin": false, "login": "suihanki", "type": "User", "id": 1302764, "followers_url": "https://api.github.com/users/suihanki/followers"}, "statuses_url": "https://api.github.com/repos/suihanki/suihanki.github.io/statuses/{sha}", "id": 31632004, "keys_url": "https://api.github.com/repos/suihanki/suihanki.github.io/keys{/key_id}", "description": "", "tags_url": "https://api.github.com/repos/suihanki/suihanki.github.io/tags", "downloads_url": "https://api.github.com/repos/suihanki/suihanki.github.io/downloads", "assignees_url": "https://api.github.com/repos/suihanki/suihanki.github.io/assignees{/user}", "contents_url": "https://api.github.com/repos/suihanki/suihanki.github.io/contents/{+path}", "has_pages": true, "git_refs_url": "https://api.github.com/repos/suihanki/suihanki.github.io/git/refs{/sha}", "open_issues_count": 1, "clone_url": "https://github.com/suihanki/suihanki.github.io.git", "watchers_count": 0, "git_tags_url": "https://api.github.com/repos/suihanki/suihanki.github.io/git/tags{/sha}", "milestones_url": "https://api.github.com/repos/suihanki/suihanki.github.io/milestones{/number}", "languages_url": "https://api.github.com/repos/suihanki/suihanki.github.io/languages", "size": 0, "homepage": null, "fork": false, "commits_url": "https://api.github.com/repos/suihanki/suihanki.github.io/commits{/sha}", "releases_url": "https://api.github.com/repos/suihanki/suihanki.github.io/releases{/id}", "issue_events_url": "https://api.github.com/repos/suihanki/suihanki.github.io/issues/events{/number}", "archive_url": "https://api.github.com/repos/suihanki/suihanki.github.io/{archive_format}{/ref}", "comments_url": "https://api.github.com/repos/suihanki/suihanki.github.io/comments{/number}", "events_url": "https://api.github.com/repos/suihanki/suihanki.github.io/events", "contributors_url": "https://api.github.com/repos/suihanki/suihanki.github.io/contributors", "html_url": "https://github.com/suihanki/suihanki.github.io", "forks": 0, "compare_url": "https://api.github.com/repos/suihanki/suihanki.github.io/compare/{base}...{head}", "open_issues": 1, "git_url": "git://github.com/suihanki/suihanki.github.io.git", "svn_url": "https://github.com/suihanki/suihanki.github.io", "merges_url": "https://api.github.com/repos/suihanki/suihanki.github.io/merges", "has_issues": true, "ssh_url": "git@github.com:suihanki/suihanki.github.io.git", "blobs_url": "https://api.github.com/repos/suihanki/suihanki.github.io/git/blobs{/sha}", "git_commits_url": "https://api.github.com/repos/suihanki/suihanki.github.io/git/commits{/sha}", "hooks_url": "https://api.github.com/repos/suihanki/suihanki.github.io/hooks", "has_downloads": true, "watchers": 0, "name": "suihanki.github.io", "language": "HTML", "url": "https://api.github.com/repos/suihanki/suihanki.github.io", "created_at": "2015-03-04T01:47:21Z", "pushed_at": "2015-03-04T22:56:20Z", "forks_count": 0, "default_branch": "master", "teams_url": "https://api.github.com/repos/suihanki/suihanki.github.io/teams", "trees_url": "https://api.github.com/repos/suihanki/suihanki.github.io/git/trees{/sha}", "branches_url": "https://api.github.com/repos/suihanki/suihanki.github.io/branches{/branch}", "subscribers_url": "https://api.github.com/repos/suihanki/suihanki.github.io/subscribers", "stargazers_url": "https://api.github.com/repos/suihanki/suihanki.github.io/stargazers"}, "sha": "571ef42bcc16ae57a4dc137ff52729fd46971b27", "ref": "test_branch", "user": {"following_url": "https://api.github.com/users/suihanki/following{/other_user}", "events_url": "https://api.github.com/users/suihanki/events{/privacy}", "organizations_url": "https://api.github.com/users/suihanki/orgs", "url": "https://api.github.com/users/suihanki", "gists_url": "https://api.github.com/users/suihanki/gists{/gist_id}", "html_url": "https://github.com/suihanki", "subscriptions_url": "https://api.github.com/users/suihanki/subscriptions", "avatar_url": "https://avatars.githubusercontent.com/u/1302764?v=3", "repos_url": "https://api.github.com/users/suihanki/repos", "received_events_url": "https://api.github.com/users/suihanki/received_events", "gravatar_id": "", "starred_url": "https://api.github.com/users/suihanki/starred{/owner}{/repo}", "site_admin": false, "login": "suihanki", "type": "User", "id": 1302764, "followers_url": "https://api.github.com/users/suihanki/followers"}, "label": "suihanki:test_branch"}, "commits_url": "https://api.github.com/repos/suihanki/suihanki.github.io/pulls/2/commits", "commits": 2, "comments_url": "https://api.github.com/repos/suihanki/suihanki.github.io/issues/2/comments", "html_url": "https://github.com/suihanki/suihanki.github.io/pull/2", "updated_at": "2015-03-04T22:57:06Z", "base": {"repo": {"issues_url": "https://api.github.com/repos/suihanki/suihanki.github.io/issues{/number}", "stargazers_count": 0, "forks_url": "https://api.github.com/repos/suihanki/suihanki.github.io/forks", "mirror_url": null, "subscription_url": "https://api.github.com/repos/suihanki/suihanki.github.io/subscription", "notifications_url": "https://api.github.com/repos/suihanki/suihanki.github.io/notifications{?since,all,participating}", "collaborators_url": "https://api.github.com/repos/suihanki/suihanki.github.io/collaborators{/collaborator}", "updated_at": "2015-03-04T22:49:09Z", "private": false, "pulls_url": "https://api.github.com/repos/suihanki/suihanki.github.io/pulls{/number}", "issue_comment_url": "https://api.github.com/repos/suihanki/suihanki.github.io/issues/comments{/number}", "labels_url": "https://api.github.com/repos/suihanki/suihanki.github.io/labels{/name}", "has_wiki": true, "full_name": "suihanki/suihanki.github.io", "owner": {"following_url": "https://api.github.com/users/suihanki/following{/other_user}", "events_url": "https://api.github.com/users/suihanki/events{/privacy}", "organizations_url": "https://api.github.com/users/suihanki/orgs", "url": "https://api.github.com/users/suihanki", "gists_url": "https://api.github.com/users/suihanki/gists{/gist_id}", "html_url": "https://github.com/suihanki", "subscriptions_url": "https://api.github.com/users/suihanki/subscriptions", "avatar_url": "https://avatars.githubusercontent.com/u/1302764?v=3", "repos_url": "https://api.github.com/users/suihanki/repos", "received_events_url": "https://api.github.com/users/suihanki/received_events", "gravatar_id": "", "starred_url": "https://api.github.com/users/suihanki/starred{/owner}{/repo}", "site_admin": false, "login": "suihanki", "type": "User", "id": 1302764, "followers_url": "https://api.github.com/users/suihanki/followers"}, "statuses_url": "https://api.github.com/repos/suihanki/suihanki.github.io/statuses/{sha}", "id": 31632004, "keys_url": "https://api.github.com/repos/suihanki/suihanki.github.io/keys{/key_id}", "description": "", "tags_url": "https://api.github.com/repos/suihanki/suihanki.github.io/tags", "downloads_url": "https://api.github.com/repos/suihanki/suihanki.github.io/downloads", "assignees_url": "https://api.github.com/repos/suihanki/suihanki.github.io/assignees{/user}", "contents_url": "https://api.github.com/repos/suihanki/suihanki.github.io/contents/{+path}", "has_pages": true, "git_refs_url": "https://api.github.com/repos/suihanki/suihanki.github.io/git/refs{/sha}", "open_issues_count": 1, "clone_url": "https://github.com/suihanki/suihanki.github.io.git", "watchers_count": 0, "git_tags_url": "https://api.github.com/repos/suihanki/suihanki.github.io/git/tags{/sha}", "milestones_url": "https://api.github.com/repos/suihanki/suihanki.github.io/milestones{/number}", "languages_url": "https://api.github.com/repos/suihanki/suihanki.github.io/languages", "size": 0, "homepage": null, "fork": false, "commits_url": "https://api.github.com/repos/suihanki/suihanki.github.io/commits{/sha}", "releases_url": "https://api.github.com/repos/suihanki/suihanki.github.io/releases{/id}", "issue_events_url": "https://api.github.com/repos/suihanki/suihanki.github.io/issues/events{/number}", "archive_url": "https://api.github.com/repos/suihanki/suihanki.github.io/{archive_format}{/ref}", "comments_url": "https://api.github.com/repos/suihanki/suihanki.github.io/comments{/number}", "events_url": "https://api.github.com/repos/suihanki/suihanki.github.io/events", "contributors_url": "https://api.github.com/repos/suihanki/suihanki.github.io/contributors", "html_url": "https://github.com/suihanki/suihanki.github.io", "forks": 0, "compare_url": "https://api.github.com/repos/suihanki/suihanki.github.io/compare/{base}...{head}", "open_issues": 1, "git_url": "git://github.com/suihanki/suihanki.github.io.git", "svn_url": "https://github.com/suihanki/suihanki.github.io", "merges_url": "https://api.github.com/repos/suihanki/suihanki.github.io/merges", "has_issues": true, "ssh_url": "git@github.com:suihanki/suihanki.github.io.git", "blobs_url": "https://api.github.com/repos/suihanki/suihanki.github.io/git/blobs{/sha}", "git_commits_url": "https://api.github.com/repos/suihanki/suihanki.github.io/git/commits{/sha}", "hooks_url": "https://api.github.com/repos/suihanki/suihanki.github.io/hooks", "has_downloads": true, "watchers": 0, "name": "suihanki.github.io", "language": "HTML", "url": "https://api.github.com/repos/suihanki/suihanki.github.io", "created_at": "2015-03-04T01:47:21Z", "pushed_at": "2015-03-04T22:56:20Z", "forks_count": 0, "default_branch": "master", "teams_url": "https://api.github.com/repos/suihanki/suihanki.github.io/teams", "trees_url": "https://api.github.com/repos/suihanki/suihanki.github.io/git/trees{/sha}", "branches_url": "https://api.github.com/repos/suihanki/suihanki.github.io/branches{/branch}", "subscribers_url": "https://api.github.com/repos/suihanki/suihanki.github.io/subscribers", "stargazers_url": "https://api.github.com/repos/suihanki/suihanki.github.io/stargazers"}, "sha": "8b94a4483403e70cfcbc41f058ce980234435e57", "ref": "master", "user": {"following_url": "https://api.github.com/users/suihanki/following{/other_user}", "events_url": "https://api.github.com/users/suihanki/events{/privacy}", "organizations_url": "https://api.github.com/users/suihanki/orgs", "url": "https://api.github.com/users/suihanki", "gists_url": "https://api.github.com/users/suihanki/gists{/gist_id}", "html_url": "https://github.com/suihanki", "subscriptions_url": "https://api.github.com/users/suihanki/subscriptions", "avatar_url": "https://avatars.githubusercontent.com/u/1302764?v=3", "repos_url": "https://api.github.com/users/suihanki/repos", "received_events_url": "https://api.github.com/users/suihanki/received_events", "gravatar_id": "", "starred_url": "https://api.github.com/users/suihanki/starred{/owner}{/repo}", "site_admin": false, "login": "suihanki", "type": "User", "id": 1302764, "followers_url": "https://api.github.com/users/suihanki/followers"}, "label": "suihanki:master"}, "user": {"following_url": "https://api.github.com/users/suihanki/following{/other_user}", "events_url": "https://api.github.com/users/suihanki/events{/privacy}", "organizations_url": "https://api.github.com/users/suihanki/orgs", "url": "https://api.github.com/users/suihanki", "gists_url": "https://api.github.com/users/suihanki/gists{/gist_id}", "html_url": "https://github.com/suihanki", "subscriptions_url": "https://api.github.com/users/suihanki/subscriptions", "avatar_url": "https://avatars.githubusercontent.com/u/1302764?v=3", "repos_url": "https://api.github.com/users/suihanki/repos", "received_events_url": "https://api.github.com/users/suihanki/received_events", "gravatar_id": "", "starred_url": "https://api.github.com/users/suihanki/starred{/owner}{/repo}", "site_admin": false, "login": "suihanki", "type": "User", "id": 1302764, "followers_url": "https://api.github.com/users/suihanki/followers"}, "milestone": null, "locked": false, "merged_by": null, "url": "https://api.github.com/repos/suihanki/suihanki.github.io/pulls/2", "mergeable_state": "unknown", "created_at": "2015-03-04T22:57:06Z", "merged": false, "review_comments_url": "https://api.github.com/repos/suihanki/suihanki.github.io/pulls/2/comments", "review_comments": 0, "review_comment_url": "https://api.github.com/repos/suihanki/suihanki.github.io/pulls/comments{/number}", "patch_url": "https://github.com/suihanki/suihanki.github.io/pull/2.patch"}}, "created_at": "2015-03-04T22:57:06Z", "actor": {"url": "https://api.github.com/users/suihanki", "login": "suihanki", "avatar_url": "https://avatars.githubusercontent.com/u/1302764?", "id": 1302764, "gravatar_id": ""}, "id": "2625207180", "repo": {"url": "https://api.github.com/repos/suihanki/suihanki.github.io", "id": 31632004, "name": "suihanki/suihanki.github.io"}, "type": "PullRequestEvent", "public": true}, {"payload": {"size": 1, "head": "44c8acca465547c8af3799fd9832ad688562030a", "commits": [{"distinct": true, "sha": "44c8acca465547c8af3799fd9832ad688562030a", "message": "Create HelloWorld.md", "url": "https://api.github.com/repos/lahunmen/datasciencecoursera/commits/44c8acca465547c8af3799fd9832ad688562030a", "author": {"email": "lahunmen@users.noreply.github.com", "name": "Bruno (LahunMen) Pinheiro"}}], "distinct_size": 1, "push_id": 592230460, "ref": "refs/heads/data-branch", "before": "45fdfd94c1635c70ada083078d90b53a87a39235"}, "created_at": "2015-03-04T22:57:06Z", "actor": {"url": "https://api.github.com/users/lahunmen", "login": "lahunmen", "avatar_url": "https://avatars.githubusercontent.com/u/4950948?", "id": 4950948, "gravatar_id": ""}, "id": "2625207179", "repo": {"url": "https://api.github.com/repos/lahunmen/datasciencecoursera", "id": 31684131, "name": "lahunmen/datasciencecoursera"}, "type": "PushEvent", "public": true}, {"payload": {"size": 4, "head": "3d3ab3a48f435c387ad242cc762398dac17227c6", "commits": [{"distinct": true, "sha": "5470857f6f88a5b34736861e42b28d994dab7643", "message": "WIP: In process of edit selected node.", "url": "https://api.github.com/repos/concord-consortium/building-models/commits/5470857f6f88a5b34736861e42b28d994dab7643", "author": {"email": "knowuh@gmail.com", "name": "Noah Paessel"}}, {"distinct": true, "sha": "6aa10059b691265b6ae971e58e0ba600a21131c7", "message": "Cleaned up some styling.  Reorganized a few things.", "url": "https://api.github.com/repos/concord-consortium/building-models/commits/6aa10059b691265b6ae971e58e0ba600a21131c7", "author": {"email": "knowuh@gmail.com", "name": "Noah Paessel"}}, {"distinct": true, "sha": "0d8a501d3c958d791edb5a6a3410ec494001a647", "message": "Can modify a node by double clicking on it [#88275098]\n\nhttps://www.pivotaltracker.com/story/show/88275098", "url": "https://api.github.com/repos/concord-consortium/building-models/commits/0d8a501d3c958d791edb5a6a3410ec494001a647", "author": {"email": "knowuh@gmail.com", "name": "Noah Paessel"}}, {"distinct": true, "sha": "3d3ab3a48f435c387ad242cc762398dac17227c6", "message": "Clean up some styling\n\nDone while delivering: https://www.pivotaltracker.com/story/show/88275098", "url": "https://api.github.com/repos/concord-consortium/building-models/commits/3d3ab3a48f435c387ad242cc762398dac17227c6", "author": {"email": "knowuh@gmail.com", "name": "Noah Paessel"}}], "distinct_size": 4, "push_id": 592230456, "ref": "refs/heads/master", "before": "24f890d1899817079fe2dbd69c75cef148f503f6"}, "created_at": "2015-03-04T22:57:06Z", "actor": {"url": "https://api.github.com/users/knowuh", "login": "knowuh", "avatar_url": "https://avatars.githubusercontent.com/u/22908?", "id": 22908, "gravatar_id": ""}, "id": "2625207169", "repo": {"url": "https://api.github.com/repos/concord-consortium/building-models", "id": 31028662, "name": "concord-consortium/building-models"}, "org": {"url": "https://api.github.com/orgs/concord-consortium", "login": "concord-consortium", "avatar_url": "https://avatars.githubusercontent.com/u/319219?", "id": 319219, "gravatar_id": ""}, "type": "PushEvent", "public": true}, {"payload": {"size": 1, "head": "5fd98576f0ec4ff5e42fcc9c8ad9d747c15fce2b", "commits": [{"distinct": true, "sha": "5fd98576f0ec4ff5e42fcc9c8ad9d747c15fce2b", "message": "Update RestTransport to honor verify and cert settings", "url": "https://api.github.com/repos/jasonjohnson/softlayer-python/commits/5fd98576f0ec4ff5e42fcc9c8ad9d747c15fce2b", "author": {"email": "spligak@gmail.com", "name": "Jason Johnson"}}], "distinct_size": 1, "push_id": 592230454, "ref": "refs/heads/rest-transport-cert-verify", "before": "b9c08ccd407e17481d6e8492aca9a0d5cc978c52"}, "created_at": "2015-03-04T22:57:06Z", "actor": {"url": "https://api.github.com/users/jasonjohnson", "login": "jasonjohnson", "avatar_url": "https://avatars.githubusercontent.com/u/31965?", "id": 31965, "gravatar_id": ""}, "id": "2625207159", "repo": {"url": "https://api.github.com/repos/jasonjohnson/softlayer-python", "id": 31684000, "name": "jasonjohnson/softlayer-python"}, "type": "PushEvent", "public": true}, {"payload": {"master_branch": "master", "ref_type": "repository", "ref": null, "description": "", "pusher_type": "user"}, "created_at": "2015-03-04T22:57:06Z", "actor": {"url": "https://api.github.com/users/jsundhar", "login": "jsundhar", "avatar_url": "https://avatars.githubusercontent.com/u/10523175?", "id": 10523175, "gravatar_id": ""}, "id": "2625207157", "repo": {"url": "https://api.github.com/repos/jsundhar/gittest", "id": 31684430, "name": "jsundhar/gittest"}, "type": "CreateEvent", "public": true}, {"payload": {"size": 1, "head": "d9c0f4029cf96a42c16e808d9f27609954699f60", "commits": [{"distinct": true, "sha": "d9c0f4029cf96a42c16e808d9f27609954699f60", "message": "", "url": "https://api.github.com/repos/PhocaCz/PhocaDownloadFinderPlugin/commits/d9c0f4029cf96a42c16e808d9f27609954699f60", "author": {"email": "info@phoca.cz", "name": "Jan"}}], "distinct_size": 1, "push_id": 592230452, "ref": "refs/heads/master", "before": "3dc11587b0f20b82fe781215ddee32e37b1a5151"}, "created_at": "2015-03-04T22:57:06Z", "actor": {"url": "https://api.github.com/users/PhocaCz", "login": "PhocaCz", "avatar_url": "https://avatars.githubusercontent.com/u/5381559?", "id": 5381559, "gravatar_id": ""}, "id": "2625207149", "repo": {"url": "https://api.github.com/repos/PhocaCz/PhocaDownloadFinderPlugin", "id": 31684429, "name": "PhocaCz/PhocaDownloadFinderPlugin"}, "type": "PushEvent", "public": true}, {"payload": {"size": 1, "head": "c70d7e4c54d56c7fe172af71c61cb5f80734b76a", "commits": [{"distinct": true, "sha": "c70d7e4c54d56c7fe172af71c61cb5f80734b76a", "message": "Update README.md", "url": "https://api.github.com/repos/beingzy/learning_dist_metrics/commits/c70d7e4c54d56c7fe172af71c61cb5f80734b76a", "author": {"email": "beingzy@gmail.com", "name": "Yi Zhang"}}], "distinct_size": 1, "push_id": 592230438, "ref": "refs/heads/master", "before": "47c6dccbf73f6093bbff794a9738686887b3d300"}, "created_at": "2015-03-04T22:57:05Z", "actor": {"url": "https://api.github.com/users/beingzy", "login": "beingzy", "avatar_url": "https://avatars.githubusercontent.com/u/859507?", "id": 859507, "gravatar_id": ""}, "id": "2625207135", "repo": {"url": "https://api.github.com/repos/beingzy/learning_dist_metrics", "id": 30219346, "name": "beingzy/learning_dist_metrics"}, "type": "PushEvent", "public": true}, {"payload": {"size": 3, "head": "7b229d58917dedb144aa66a584d99e944768442f", "commits": [{"distinct": true, "sha": "65b841a3867c6b5797e53b7af9ae4c8df4b98535", "message": "adding mozuHosted switch", "url": "https://api.github.com/repos/Mozu/mozu-node-sdk/commits/65b841a3867c6b5797e53b7af9ae4c8df4b98535", "author": {"email": "thomas_phipps@volusion.com", "name": "Sparkel Phipps"}}, {"distinct": true, "sha": "2fd7d399e0f767977091f4d6905cc4aa3d36beca", "message": "optimizing make-method", "url": "https://api.github.com/repos/Mozu/mozu-node-sdk/commits/2fd7d399e0f767977091f4d6905cc4aa3d36beca", "author": {"email": "zetlen@gmail.com", "name": "james"}}, {"distinct": true, "sha": "7b229d58917dedb144aa66a584d99e944768442f", "message": "0.12.0", "url": "https://api.github.com/repos/Mozu/mozu-node-sdk/commits/7b229d58917dedb144aa66a584d99e944768442f", "author": {"email": "zetlen@gmail.com", "name": "james"}}], "distinct_size": 3, "push_id": 592230435, "ref": "refs/heads/master", "before": "bf95ee27b417aa1f25530b82acd22e7a62f8e09e"}, "created_at": "2015-03-04T22:57:05Z", "actor": {"url": "https://api.github.com/users/zetlen", "login": "zetlen", "avatar_url": "https://avatars.githubusercontent.com/u/1643758?", "id": 1643758, "gravatar_id": ""}, "id": "2625207130", "repo": {"url": "https://api.github.com/repos/Mozu/mozu-node-sdk", "id": 27494589, "name": "Mozu/mozu-node-sdk"}, "org": {"url": "https://api.github.com/orgs/Mozu", "login": "Mozu", "avatar_url": "https://avatars.githubusercontent.com/u/2609243?", "id": 2609243, "gravatar_id": ""}, "type": "PushEvent", "public": true}, {"payload": {"size": 1, "head": "6fa9c39ed6f33940351cd3f95f13cf792bb4525a", "commits": [{"distinct": true, "sha": "6fa9c39ed6f33940351cd3f95f13cf792bb4525a", "message": "working test", "url": "https://api.github.com/repos/amco/dolly/commits/6fa9c39ed6f33940351cd3f95f13cf792bb4525a", "author": {"email": "seanc@amcoonline.net", "name": "seancookr"}}], "distinct_size": 1, "push_id": 592230434, "ref": "refs/heads/50-read-property-not-working-correctly", "before": "17d0970ecba838ec4291a36871b0fd14fc29d806"}, "created_at": "2015-03-04T22:57:05Z", "actor": {"url": "https://api.github.com/users/seancookr", "login": "seancookr", "avatar_url": "https://avatars.githubusercontent.com/u/3506743?", "id": 3506743, "gravatar_id": ""}, "id": "2625207127", "repo": {"url": "https://api.github.com/repos/amco/dolly", "id": 13510618, "name": "amco/dolly"}, "org": {"url": "https://api.github.com/orgs/amco", "login": "amco", "avatar_url": "https://avatars.githubusercontent.com/u/137698?", "id": 137698, "gravatar_id": ""}, "type": "PushEvent", "public": true}]